ALU.v
`define AND 4'b0000
`define OR 4'b0001
`define ADD 4'b0010
`define SUB 4'b0110
`define PassB 4'b0111

module ALU(BusW,Zero,BusA,BusB,ALUCtrl);
output reg [63:0]BusW;
output Zero;
input [63:0] BusA,BusB;
input [3:0]ALUCtrl;
always @ (ALUCtrl, BusA,BusB)
case(ALUCtrl)
`AND: BusW = BusA & BusB;
`OR:  BusW = BusA | BusB;
`ADD: BusW = BusA + BusB;
`SUB: BusW = BusA - BusB;
`PassB: 
begin
    BusW = BusB;
end
endcase
assign  Zero = (BusB==0);
endmodule

ALUTest.v
`timescale 1ns / 1ps

////////////////////////////////////////////////////////////////////////////////
// Company: 
// Engineer:
//
// Create Date:   10:02:47 03/05/2009
// Design Name:   ALU
// Module Name:   E:/350/Lab8/ALU/ALUTest.v
// Project Name:  ALU
// Target Device:  
// Tool versions:  
// Description: 
//
// Verilog Test Fixture created by ISE for module: ALU
//
// Dependencies:
// 
// Revision:
// Revision 0.01 - File Created
// Additional Comments:
// 
////////////////////////////////////////////////////////////////////////////////

`define STRLEN 32
module ALUTest_v;
initial
   begin
     $dumpfile("ALU.vcd"); // the string inside the double quotation is the name of the .vcd file to be generated, you name it.
     $dumpvars(0,ALUTest_v); // the 2nd parameter is your test module name, which is in the very first line!
  end
	task passTest;
		input [64:0] actualOut, expectedOut;
		input [`STRLEN*8:0] testType;
		inout [7:0] passed;
	
		if(actualOut == expectedOut) begin $display ("%s passed", testType); passed = passed + 1; end
		else $display ("%s failed: %x should be %x", testType, actualOut, expectedOut);
	endtask
	
	task allPassed;
		input [7:0] passed;
		input [7:0] numTests;
		
		if(passed == numTests) $display ("All tests passed");
		else $display("Some tests failed. Passed %x. Total tests: %x", passed, numTests);
	endtask

	// Inputs
	reg [63:0] BusA;
	reg [63:0] BusB;
	reg [3:0] ALUCtrl;
	reg [7:0] passed;

	// Outputs
	wire [63:0] BusW;
	wire Zero;

	// Instantiate the Unit Under Test (UUT)
	ALU uut (
		.BusW(BusW), 
		.Zero(Zero), 
		.BusA(BusA), 
		.BusB(BusB), 
		.ALUCtrl(ALUCtrl)
	);

	initial begin
		// Initialize Inputs
		BusA = 0;
		BusB = 0;
		ALUCtrl = 0;
		passed = 0;


		{BusA, BusB, ALUCtrl} = {64'h20, 64'h4500, 4'h2}; #40; passTest({Zero, BusW}, 65'h04520, "ADD 0x20,0x4500", passed);
		{BusA, BusB, ALUCtrl} = {64'h23BCF6, 64'h5B86, 4'h2}; #40; passTest({Zero, BusW}, 65'h24187C, "ADD 0x1234,0xABCD0000", passed);
		{BusA, BusB, ALUCtrl} = {64'h5EC74E3, 64'h487CD8838D, 4'h2}; #40; passTest({Zero, BusW}, 65'h4882C4F870, "ADD 0x1234,0xABCD0000", passed);

		{BusA, BusB, ALUCtrl} = {64'h53F15, 64'h17177, 4'h0}; #40; passTest({Zero, BusW}, 65'h13115, "AND 0x53F15,0x17177", passed);
		{BusA, BusB, ALUCtrl} = {64'hDA0, 64'h23BB, 4'h0}; #40; passTest({Zero, BusW}, 65'h1A0, "AND 0xDA0,0xABCD0000", passed);
		{BusA, BusB, ALUCtrl} = {64'h18667, 64'h3BE61, 4'h0}; #40; passTest({Zero, BusW}, 65'h18661, "AND 0x18667,0x3BE61", passed);

		{BusA, BusB, ALUCtrl} = {64'h98967F, 64'hA98AC7, 4'h1}; #40; passTest({Zero, BusW}, 65'hB99EFF, "OR 0x98967F,0xA98AC7", passed);
		{BusA, BusB, ALUCtrl} = {64'h73BBF6, 64'h1, 4'h1}; #40; passTest({Zero, BusW}, 65'h73BBF7, "OR 0x73BBF6,0x1", passed);
		{BusA, BusB, ALUCtrl} = {64'h319384, 64'h01304213, 4'h1}; #40; passTest({Zero, BusW}, 65'h131D397, "OR 0x319384,0x01304213", passed);

		{BusA, BusB, ALUCtrl} = {64'h19E0711F, 64'h2246274, 4'h6}; #40; passTest({Zero, BusW}, 65'h17BC0EAB, "SUB 0x19E0711F,0x2246274", passed);
		{BusA, BusB, ALUCtrl} = {64'hFEDCBA, 64'hABCDEF, 4'h6}; #40; passTest({Zero, BusW}, 65'h530ECB, "SUB 0xFEDCBA,0xABCDEF", passed);
		{BusA, BusB, ALUCtrl} = {64'h328FEDAF, 64'hAB879CD, 4'h6}; #40; passTest({Zero, BusW}, 65'h27D773E2, "SUB 0x328FEDAF,0xAB879CD", passed);

		{BusA, BusB, ALUCtrl} = {64'h0, 64'hFFF, 4'h7}; #40; passTest({Zero, BusW}, 65'hFFF, "PassB 0x0,0xFFF", passed);
		{BusA, BusB, ALUCtrl} = {64'h999, 64'h0, 4'h7}; #40; passTest({Zero, BusW}, 65'h10000000000000000, "PassB 0x999,0x0", passed);
		{BusA, BusB, ALUCtrl} = {64'h0, 64'h0, 4'h7}; #40; passTest({Zero, BusW}, 65'h10000000000000000, "PassB 0x0,0x0", passed);

		allPassed(passed, 15);
	end    
endmodule

/*ADD1, 2, 20, 4500, 0, 4520
ADD2, 2,23BCF6 , 5B86, 0, 24187C
ADD3, 2, 5EC74E3, 487CD8838D, 0, 4882C4F870

AND1,0, 53F15,17177,0,13115
AND2,0, DA0,23BB,0,1A0
AND3,0, 18667,3BE61,0,18661

OR1,1,98967F,A98AC7,0,B99EFF
OR2,1,73BBF6,1,0,73BBF7
OR3,1,319384,01304213,0,131D397

SUB,6,19E0711F,2246274,0,17BC0EAB
SUB,6,FEDCBA,ABCDEF,0,530ECB
SUB,6,328FEDAF,AB879CD,0,27D773E2

PassB,7,0,FFF,0,FFF
PassB,7,999,0,1, 0
PassB,7,0,0,1,0*/

ALU.vcd
$date
	Mon Apr 17 06:06:14 2023
$end
$version
	Icarus Verilog
$end
$timescale
	1ps
$end
$scope module ALUTest_v $end
$var wire 1 ! Zero $end
$var wire 64 " BusW [63:0] $end
$var reg 4 # ALUCtrl [3:0] $end
$var reg 64 $ BusA [63:0] $end
$var reg 64 % BusB [63:0] $end
$var reg 8 & passed [7:0] $end
$scope module uut $end
$var wire 4 ' ALUCtrl [3:0] $end
$var wire 64 ( BusA [63:0] $end
$var wire 64 ) BusB [63:0] $end
$var wire 1 ! Zero $end
$var reg 64 * BusW [63:0] $end
$upscope $end
$scope task allPassed $end
$var reg 8 + numTests [7:0] $end
$var reg 8 , passed [7:0] $end
$upscope $end
$scope task passTest $end
$var reg 65 - actualOut [64:0] $end
$var reg 65 . expectedOut [64:0] $end
$var reg 8 / passed [7:0] $end
$var reg 257 0 testType [256:0] $end
$upscope $end
$upscope $end
$enddefinitions $end
#0
$dumpvars
bx 0
bx /
bx .
bx -
bx ,
bx +
b100010100100000 *
b100010100000000 )
b100000 (
b10 '
b0 &
b100010100000000 %
b100000 $
b10 #
b100010100100000 "
0!
$end
#40000
b1001000001100001111100 "
b1001000001100001111100 *
b1000111011110011110110 $
b1000111011110011110110 (
b101101110000110 %
b101101110000110 )
b1 &
b1 /
b10000010100010001000100001000000011000001111000001100100011000000101100001100000111100000110100001101010011000000110000 0
b100010100100000 .
b100010100100000 -
#80000
b100100010000010110001001111100001110000 "
b100100010000010110001001111100001110000 *
b101111011000111010011100011 $
b101111011000111010011100011 (
b100100001111100110110001000001110001101 %
b100100001111100110110001000001110001101 )
b10 &
b10 /
b10000010100010001000100001000000011000001111000001100010011001000110011001101000010110000110000011110000100000101000010010000110100010000110000001100000011000000110000 0
b1001000001100001111100 .
b1001000001100001111100 -
#120000
b10011000100010101 "
b10011000100010101 *
b1010011111100010101 $
b1010011111100010101 (
b10111000101110111 %
b10111000101110111 )
b0 #
b0 '
b11 &
b11 /
b100100010000010110001001111100001110000 .
b100100010000010110001001111100001110000 -
#160000
b110100000 "
b110100000 *
b110110100000 $
b110110100000 (
b10001110111011 %
b10001110111011 )
b100 &
b100 /
b1000001010011100100010000100000001100000111100000110101001100110100011000110001001101010010110000110000011110000011000100110111001100010011011100110111 0
b10011000100010101 .
b10011000100010101 -
#200000
b11000011001100001 "
b11000011001100001 *
b11000011001100111 $
b11000011001100111 (
b111011111001100001 %
b111011111001100001 )
b101 &
b101 /
b100000101001110010001000010000000110000011110000100010001000001001100000010110000110000011110000100000101000010010000110100010000110000001100000011000000110000 0
b110100000 .
b110100000 -
#240000
b101110011001111011111111 "
b101110011001111011111111 *
b100110001001011001111111 $
b100110001001011001111111 (
b101010011000101011000111 %
b101010011000101011000111 )
b1 #
b1 '
b110 &
b110 /
b1000001010011100100010000100000001100000111100000110001001110000011011000110110001101110010110000110000011110000011001101000010010001010011011000110001 0
b11000011001100001 .
b11000011001100001 -
#280000
b11100111011101111110111 "
b11100111011101111110111 *
b11100111011101111110110 $
b11100111011101111110110 (
b1 %
b1 )
b111 &
b111 /
b100111101010010001000000011000001111000001110010011100000111001001101100011011101000110001011000011000001111000010000010011100100111000010000010100001100110111 0
b101110011001111011111111 .
b101110011001111011111111 -
#320000
b1001100011101001110010111 "
b1001100011101001110010111 *
b1100011001001110000100 $
b1100011001001110000100 (
b1001100000100001000010011 %
b1001100000100001000010011 )
b1000 &
b1000 /
b10011110101001000100000001100000111100000110111001100110100001001000010010001100011011000101100001100000111100000110001 0
b11100111011101111110111 .
b11100111011101111110111 -
#360000
b10111101111000000111010101011 "
b10111101111000000111010101011 *
b11001111000000111000100011111 $
b11001111000000111000100011111 (
b10001001000110001001110100 %
b10001001000110001001110100 )
b110 #
b110 '
b1001 &
b1001 /
b1001111010100100010000000110000011110000011001100110001001110010011001100111000001101000010110000110000011110000011000000110001001100110011000000110100001100100011000100110011 0
b1001100011101001110010111 .
b1001100011101001110010111 -
#400000
b10100110000111011001011 "
b10100110000111011001011 *
b111111101101110010111010 $
b111111101101110010111010 (
b101010111100110111101111 %
b101010111100110111101111 )
b1010 &
b1010 /
b10100110101010101000010001000000011000001111000001100010011100101000101001100000011011100110001001100010100011000101100001100000111100000110010001100100011010000110110001100100011011100110100 0
b10111101111000000111010101011 .
b10111101111000000111010101011 -
#440000
b100111110101110111001111100010 "
b100111110101110111001111100010 *
b110010100011111110110110101111 $
b110010100011111110110110101111 (
b1010101110000111100111001101 %
b1010101110000111100111001101 )
b1011 &
b1011 /
b10100110101010101000010001000000011000001111000010001100100010101000100010000110100001001000001001011000011000001111000010000010100001001000011010001000100010101000110 0
b10100110000111011001011 .
b10100110000111011001011 -
#480000
b111111111111 "
b111111111111 *
b0 $
b0 (
b111111111111 %
b111111111111 )
b111 #
b111 '
b1100 &
b1100 /
b10100110101010101000010001000000011000001111000001100110011001000111000010001100100010101000100010000010100011000101100001100000111100001000001010000100011100000110111001110010100001101000100 0
b100111110101110111001111100010 .
b100111110101110111001111100010 -
#520000
b0 "
b0 *
b100110011001 $
b100110011001 (
1!
b0 %
b0 )
b1101 &
b1101 /
b10100000110000101110011011100110100001000100000001100000111100000110000001011000011000001111000010001100100011001000110 0
b111111111111 .
b111111111111 -
#560000
b0 $
b0 (
b1110 &
b1110 /
b10100000110000101110011011100110100001000100000001100000111100000111001001110010011100100101100001100000111100000110000 0
b10000000000000000000000000000000000000000000000000000000000000000 .
b10000000000000000000000000000000000000000000000000000000000000000 -
#600000
b1111 +
b1111 ,
b1111 &
b1111 /
b1010000011000010111001101110011010000100010000000110000011110000011000000101100001100000111100000110000 0
